pydantic_neo4j/__init__.py
pydantic_neo4j/create_operations.py
pydantic_neo4j/database_operations.py
pydantic_neo4j/exceptions.py
pydantic_neo4j/graph_base_models.py
pydantic_neo4j/match_operations.py
pydantic_neo4j/pydantic_neo4j.py
pydantic_neo4j-0.3.7.dist-info/METADATA
pydantic_neo4j-0.3.7.dist-info/WHEEL
pydantic_neo4j-0.3.7.dist-info/RECORD
